{
    "0599100000430863": {
        "Archetype ID": "D.2006-2014",
        "Construction Year": 2006,
        "Number of Floors": 3,
        "Wall Area": 298.04,
        "Roof Area (Flat)": 40.12,
        "Roof Area (Sloped)": 113.63,
        "Floor Area": 126.44,
        "Shared Wall Area": 0.0,
        "Absolute Height (70%)": 7.717968225479126,
        "Surfaces": [
            {
                "Coordinates": [
                    [
                        [
                            861,
                            8073,
                            0
                        ],
                        [
                            0,
                            8781,
                            0
                        ],
                        [
                            4111,
                            13760,
                            0
                        ],
                        [
                            5583,
                            12544,
                            0
                        ],
                        [
                            7938,
                            15381,
                            0
                        ],
                        [
                            14375,
                            10040,
                            0
                        ],
                        [
                            12067,
                            7235,
                            0
                        ],
                        [
                            13335,
                            6185,
                            0
                        ],
                        [
                            8250,
                            0,
                            0
                        ],
                        [
                            3847,
                            3683,
                            0
                        ],
                        [
                            3401,
                            3141,
                            0
                        ],
                        [
                            3184,
                            3409,
                            0
                        ],
                        [
                            2661,
                            3236,
                            0
                        ],
                        [
                            422,
                            5081,
                            0
                        ],
                        [
                            1120,
                            5922,
                            0
                        ],
                        [
                            617,
                            6394,
                            0
                        ],
                        [
                            667,
                            6406,
                            0
                        ],
                        [
                            815,
                            6336,
                            0
                        ],
                        [
                            693,
                            6487,
                            0
                        ],
                        [
                            1200,
                            7110,
                            0
                        ],
                        [
                            1151,
                            7158,
                            0
                        ],
                        [
                            1433,
                            7503,
                            0
                        ],
                        [
                            820,
                            8016,
                            0
                        ]
                    ]
                ],
                "Type": "G"
            },
            {
                "Coordinates": [
                    [
                        [
                            8250,
                            0,
                            7878
                        ],
                        [
                            8250,
                            0,
                            0
                        ],
                        [
                            13335,
                            6185,
                            0
                        ],
                        [
                            13335,
                            6185,
                            7878
                        ]
                    ]
                ],
                "Type": "F"
            },
            {
                "Coordinates": [
                    [
                        [
                            13335,
                            6185,
                            7878
                        ],
                        [
                            13335,
                            6185,
                            0
                        ],
                        [
                            12067,
                            7235,
                            0
                        ],
                        [
                            12067,
                            7235,
                            7878
                        ]
                    ]
                ],
                "Type": "F"
            },
            {
                "Coordinates": [
                    [
                        [
                            12067,
                            7235,
                            7878
                        ],
                        [
                            12067,
                            7235,
                            0
                        ],
                        [
                            14375,
                            10040,
                            0
                        ],
                        [
                            14375,
                            10040,
                            7878
                        ]
                    ]
                ],
                "Type": "F"
            },
            {
                "Coordinates": [
                    [
                        [
                            14375,
                            10040,
                            7878
                        ],
                        [
                            14375,
                            10040,
                            0
                        ],
                        [
                            7938,
                            15381,
                            0
                        ],
                        [
                            7938,
                            15381,
                            7878
                        ]
                    ]
                ],
                "Type": "F"
            },
            {
                "Coordinates": [
                    [
                        [
                            3847,
                            3683,
                            7878
                        ],
                        [
                            3847,
                            3683,
                            0
                        ],
                        [
                            8250,
                            0,
                            0
                        ],
                        [
                            8250,
                            0,
                            7878
                        ]
                    ]
                ],
                "Type": "F"
            },
            {
                "Coordinates": [
                    [
                        [
                            1120,
                            5922,
                            7878
                        ],
                        [
                            1120,
                            5922,
                            0
                        ],
                        [
                            422,
                            5081,
                            0
                        ],
                        [
                            422,
                            5081,
                            7878
                        ]
                    ]
                ],
                "Type": "F"
            },
            {
                "Coordinates": [
                    [
                        [
                            422,
                            5081,
                            7878
                        ],
                        [
                            422,
                            5081,
                            0
                        ],
                        [
                            2661,
                            3236,
                            0
                        ],
                        [
                            2661,
                            3236,
                            7878
                        ]
                    ]
                ],
                "Type": "F"
            },
            {
                "Coordinates": [
                    [
                        [
                            7938,
                            15381,
                            7878
                        ],
                        [
                            7938,
                            15381,
                            0
                        ],
                        [
                            5583,
                            12544,
                            0
                        ],
                        [
                            5583,
                            12544,
                            7878
                        ]
                    ]
                ],
                "Type": "F"
            },
            {
                "Coordinates": [
                    [
                        [
                            5583,
                            12544,
                            7878
                        ],
                        [
                            5583,
                            12544,
                            0
                        ],
                        [
                            4111,
                            13760,
                            0
                        ],
                        [
                            4111,
                            13760,
                            7878
                        ]
                    ]
                ],
                "Type": "F"
            },
            {
                "Coordinates": [
                    [
                        [
                            0,
                            8781,
                            7878
                        ],
                        [
                            0,
                            8781,
                            0
                        ],
                        [
                            861,
                            8073,
                            0
                        ],
                        [
                            861,
                            8073,
                            7878
                        ]
                    ]
                ],
                "Type": "F"
            },
            {
                "Coordinates": [
                    [
                        [
                            4111,
                            13760,
                            7878
                        ],
                        [
                            4111,
                            13760,
                            0
                        ],
                        [
                            0,
                            8781,
                            0
                        ],
                        [
                            0,
                            8781,
                            7878
                        ]
                    ]
                ],
                "Type": "F"
            },
            {
                "Coordinates": [
                    [
                        [
                            815,
                            6336,
                            7878
                        ],
                        [
                            815,
                            6336,
                            0
                        ],
                        [
                            667,
                            6406,
                            0
                        ],
                        [
                            667,
                            6406,
                            7878
                        ]
                    ]
                ],
                "Type": "F"
            },
            {
                "Coordinates": [
                    [
                        [
                            861,
                            8073,
                            7878
                        ],
                        [
                            861,
                            8073,
                            0
                        ],
                        [
                            820,
                            8016,
                            0
                        ],
                        [
                            820,
                            8016,
                            7878
                        ]
                    ]
                ],
                "Type": "F"
            },
            {
                "Coordinates": [
                    [
                        [
                            667,
                            6406,
                            7878
                        ],
                        [
                            667,
                            6406,
                            0
                        ],
                        [
                            617,
                            6394,
                            0
                        ],
                        [
                            617,
                            6394,
                            7878
                        ]
                    ]
                ],
                "Type": "F"
            },
            {
                "Coordinates": [
                    [
                        [
                            820,
                            8016,
                            7878
                        ],
                        [
                            820,
                            8016,
                            0
                        ],
                        [
                            1433,
                            7503,
                            0
                        ],
                        [
                            1433,
                            7503,
                            7878
                        ]
                    ]
                ],
                "Type": "F"
            },
            {
                "Coordinates": [
                    [
                        [
                            2661,
                            3236,
                            7878
                        ],
                        [
                            2661,
                            3236,
                            0
                        ],
                        [
                            3184,
                            3409,
                            0
                        ],
                        [
                            3184,
                            3409,
                            7878
                        ]
                    ]
                ],
                "Type": "F"
            },
            {
                "Coordinates": [
                    [
                        [
                            3401,
                            3141,
                            7878
                        ],
                        [
                            3401,
                            3141,
                            0
                        ],
                        [
                            3847,
                            3683,
                            0
                        ],
                        [
                            3847,
                            3683,
                            7878
                        ]
                    ]
                ],
                "Type": "F"
            },
            {
                "Coordinates": [
                    [
                        [
                            3184,
                            3409,
                            7878
                        ],
                        [
                            3184,
                            3409,
                            0
                        ],
                        [
                            3401,
                            3141,
                            0
                        ],
                        [
                            3401,
                            3141,
                            7878
                        ]
                    ]
                ],
                "Type": "F"
            },
            {
                "Coordinates": [
                    [
                        [
                            617,
                            6394,
                            7878
                        ],
                        [
                            617,
                            6394,
                            0
                        ],
                        [
                            1120,
                            5922,
                            0
                        ],
                        [
                            1120,
                            5922,
                            7878
                        ]
                    ]
                ],
                "Type": "F"
            },
            {
                "Coordinates": [
                    [
                        [
                            1433,
                            7503,
                            7878
                        ],
                        [
                            1433,
                            7503,
                            0
                        ],
                        [
                            1151,
                            7158,
                            0
                        ],
                        [
                            1151,
                            7158,
                            7878
                        ]
                    ]
                ],
                "Type": "F"
            },
            {
                "Coordinates": [
                    [
                        [
                            1151,
                            7158,
                            7878
                        ],
                        [
                            1151,
                            7158,
                            0
                        ],
                        [
                            1200,
                            7110,
                            0
                        ],
                        [
                            1200,
                            7110,
                            7878
                        ]
                    ]
                ],
                "Type": "F"
            },
            {
                "Coordinates": [
                    [
                        [
                            693,
                            6487,
                            7878
                        ],
                        [
                            693,
                            6487,
                            0
                        ],
                        [
                            815,
                            6336,
                            0
                        ],
                        [
                            815,
                            6336,
                            7878
                        ]
                    ]
                ],
                "Type": "F"
            },
            {
                "Coordinates": [
                    [
                        [
                            1200,
                            7110,
                            7878
                        ],
                        [
                            1200,
                            7110,
                            0
                        ],
                        [
                            693,
                            6487,
                            0
                        ],
                        [
                            693,
                            6487,
                            7878
                        ]
                    ]
                ],
                "Type": "F"
            },
            {
                "Coordinates": [
                    [
                        [
                            1200,
                            7110,
                            7878
                        ],
                        [
                            693,
                            6487,
                            7878
                        ],
                        [
                            815,
                            6336,
                            7878
                        ],
                        [
                            667,
                            6406,
                            7878
                        ],
                        [
                            617,
                            6394,
                            7878
                        ],
                        [
                            1120,
                            5922,
                            7878
                        ],
                        [
                            422,
                            5081,
                            7878
                        ],
                        [
                            2661,
                            3236,
                            7878
                        ],
                        [
                            3184,
                            3409,
                            7878
                        ],
                        [
                            3401,
                            3141,
                            7878
                        ],
                        [
                            3847,
                            3683,
                            7878
                        ],
                        [
                            8250,
                            0,
                            7878
                        ],
                        [
                            13335,
                            6185,
                            7878
                        ],
                        [
                            12067,
                            7235,
                            7878
                        ],
                        [
                            14375,
                            10040,
                            7878
                        ],
                        [
                            7938,
                            15381,
                            7878
                        ],
                        [
                            5583,
                            12544,
                            7878
                        ],
                        [
                            4111,
                            13760,
                            7878
                        ],
                        [
                            0,
                            8781,
                            7878
                        ],
                        [
                            861,
                            8073,
                            7878
                        ],
                        [
                            820,
                            8016,
                            7878
                        ],
                        [
                            1433,
                            7503,
                            7878
                        ],
                        [
                            1151,
                            7158,
                            7878
                        ]
                    ]
                ],
                "Type": "R"
            }
        ]
    }
}