{
    "0599100000282017": {
        "Archetype ID": "TI.1992-2005",
        "Construction Year": 1993,
        "Number of Floors": 3,
        "Wall Area": 85.34,
        "Roof Area (Flat)": 0.0,
        "Roof Area (Sloped)": 109.22,
        "Floor Area": 87.12,
        "Shared Wall Area": 190.03,
        "Absolute Height (70%)": 8.020708352327347,
        "Surfaces": [
            {
                "Coordinates": [
                    [
                        [
                            11807,
                            10779,
                            219
                        ],
                        [
                            12516,
                            9730,
                            219
                        ],
                        [
                            14976,
                            11420,
                            219
                        ],
                        [
                            16177,
                            9669,
                            219
                        ],
                        [
                            2087,
                            0,
                            219
                        ],
                        [
                            1356,
                            1069,
                            219
                        ],
                        [
                            2837,
                            2089,
                            219
                        ],
                        [
                            0,
                            6211,
                            219
                        ],
                        [
                            10410,
                            13351,
                            219
                        ],
                        [
                            12057,
                            10949,
                            219
                        ]
                    ]
                ],
                "Type": "G"
            },
            {
                "Coordinates": [
                    [
                        [
                            2087,
                            0,
                            8291
                        ],
                        [
                            2087,
                            0,
                            219
                        ],
                        [
                            16177,
                            9669,
                            219
                        ],
                        [
                            16177,
                            9669,
                            8291
                        ]
                    ]
                ],
                "Type": "F"
            },
            {
                "Coordinates": [
                    [
                        [
                            12516,
                            9730,
                            8291
                        ],
                        [
                            12516,
                            9730,
                            219
                        ],
                        [
                            11807,
                            10779,
                            219
                        ],
                        [
                            11807,
                            10779,
                            8291
                        ]
                    ]
                ],
                "Type": "F"
            },
            {
                "Coordinates": [
                    [
                        [
                            10410,
                            13351,
                            8291
                        ],
                        [
                            10410,
                            13351,
                            219
                        ],
                        [
                            0,
                            6211,
                            219
                        ],
                        [
                            0,
                            6211,
                            8291
                        ]
                    ]
                ],
                "Type": "F"
            },
            {
                "Coordinates": [
                    [
                        [
                            2837,
                            2089,
                            8291
                        ],
                        [
                            2837,
                            2089,
                            219
                        ],
                        [
                            1356,
                            1069,
                            219
                        ],
                        [
                            1356,
                            1069,
                            8291
                        ]
                    ]
                ],
                "Type": "F"
            },
            {
                "Coordinates": [
                    [
                        [
                            0,
                            6211,
                            8291
                        ],
                        [
                            0,
                            6211,
                            219
                        ],
                        [
                            2837,
                            2089,
                            219
                        ],
                        [
                            2837,
                            2089,
                            8291
                        ]
                    ]
                ],
                "Type": "F"
            },
            {
                "Coordinates": [
                    [
                        [
                            1356,
                            1069,
                            8291
                        ],
                        [
                            1356,
                            1069,
                            219
                        ],
                        [
                            2087,
                            0,
                            219
                        ],
                        [
                            2087,
                            0,
                            8291
                        ]
                    ]
                ],
                "Type": "F"
            },
            {
                "Coordinates": [
                    [
                        [
                            16177,
                            9669,
                            8291
                        ],
                        [
                            16177,
                            9669,
                            219
                        ],
                        [
                            14976,
                            11420,
                            219
                        ],
                        [
                            14976,
                            11420,
                            8291
                        ]
                    ]
                ],
                "Type": "F"
            },
            {
                "Coordinates": [
                    [
                        [
                            14976,
                            11420,
                            8291
                        ],
                        [
                            14976,
                            11420,
                            219
                        ],
                        [
                            12516,
                            9730,
                            219
                        ],
                        [
                            12516,
                            9730,
                            8291
                        ]
                    ]
                ],
                "Type": "F"
            },
            {
                "Coordinates": [
                    [
                        [
                            12057,
                            10949,
                            8291
                        ],
                        [
                            12057,
                            10949,
                            219
                        ],
                        [
                            10410,
                            13351,
                            219
                        ],
                        [
                            10410,
                            13351,
                            8291
                        ]
                    ]
                ],
                "Type": "F"
            },
            {
                "Coordinates": [
                    [
                        [
                            11807,
                            10779,
                            8291
                        ],
                        [
                            11807,
                            10779,
                            219
                        ],
                        [
                            12057,
                            10949,
                            219
                        ],
                        [
                            12057,
                            10949,
                            8291
                        ]
                    ]
                ],
                "Type": "F"
            },
            {
                "Coordinates": [
                    [
                        [
                            11807,
                            10779,
                            8291
                        ],
                        [
                            12057,
                            10949,
                            8291
                        ],
                        [
                            10410,
                            13351,
                            8291
                        ],
                        [
                            0,
                            6211,
                            8291
                        ],
                        [
                            2837,
                            2089,
                            8291
                        ],
                        [
                            1356,
                            1069,
                            8291
                        ],
                        [
                            2087,
                            0,
                            8291
                        ],
                        [
                            16177,
                            9669,
                            8291
                        ],
                        [
                            14976,
                            11420,
                            8291
                        ],
                        [
                            12516,
                            9730,
                            8291
                        ]
                    ]
                ],
                "Type": "R"
            }
        ]
    }
}