{
    "0599100000344945": {
        "Archetype ID": "TI.1992-2005",
        "Construction Year": 1996,
        "Number of Floors": 3,
        "Wall Area": 108.04,
        "Roof Area (Flat)": 7.27,
        "Roof Area (Sloped)": 55.08,
        "Floor Area": 58.61,
        "Shared Wall Area": 161.38,
        "Absolute Height (70%)": 8.111143350601196,
        "Surfaces": [
            {
                "Coordinates": [
                    [
                        [
                            814,
                            3138,
                            0
                        ],
                        [
                            966,
                            3582,
                            0
                        ],
                        [
                            2304,
                            3123,
                            0
                        ],
                        [
                            5409,
                            11927,
                            0
                        ],
                        [
                            10508,
                            10155,
                            0
                        ],
                        [
                            7411,
                            1370,
                            0
                        ],
                        [
                            3726,
                            2634,
                            0
                        ],
                        [
                            2800,
                            0,
                            0
                        ],
                        [
                            0,
                            961,
                            0
                        ],
                        [
                            756,
                            3153,
                            0
                        ]
                    ]
                ],
                "Type": "G"
            },
            {
                "Coordinates": [
                    [
                        [
                            756,
                            3153,
                            8168
                        ],
                        [
                            756,
                            3153,
                            0
                        ],
                        [
                            0,
                            961,
                            0
                        ],
                        [
                            0,
                            961,
                            8168
                        ]
                    ]
                ],
                "Type": "F"
            },
            {
                "Coordinates": [
                    [
                        [
                            2304,
                            3123,
                            8168
                        ],
                        [
                            2304,
                            3123,
                            0
                        ],
                        [
                            966,
                            3582,
                            0
                        ],
                        [
                            966,
                            3582,
                            8168
                        ]
                    ]
                ],
                "Type": "F"
            },
            {
                "Coordinates": [
                    [
                        [
                            5409,
                            11927,
                            8168
                        ],
                        [
                            5409,
                            11927,
                            0
                        ],
                        [
                            2304,
                            3123,
                            0
                        ],
                        [
                            2304,
                            3123,
                            8168
                        ]
                    ]
                ],
                "Type": "F"
            },
            {
                "Coordinates": [
                    [
                        [
                            2800,
                            0,
                            8168
                        ],
                        [
                            2800,
                            0,
                            0
                        ],
                        [
                            3726,
                            2634,
                            0
                        ],
                        [
                            3726,
                            2634,
                            8168
                        ]
                    ]
                ],
                "Type": "F"
            },
            {
                "Coordinates": [
                    [
                        [
                            0,
                            961,
                            8168
                        ],
                        [
                            0,
                            961,
                            0
                        ],
                        [
                            2800,
                            0,
                            0
                        ],
                        [
                            2800,
                            0,
                            8168
                        ]
                    ]
                ],
                "Type": "F"
            },
            {
                "Coordinates": [
                    [
                        [
                            3726,
                            2634,
                            8168
                        ],
                        [
                            3726,
                            2634,
                            0
                        ],
                        [
                            7411,
                            1370,
                            0
                        ],
                        [
                            7411,
                            1370,
                            8168
                        ]
                    ]
                ],
                "Type": "F"
            },
            {
                "Coordinates": [
                    [
                        [
                            7411,
                            1370,
                            8168
                        ],
                        [
                            7411,
                            1370,
                            0
                        ],
                        [
                            10508,
                            10155,
                            0
                        ],
                        [
                            10508,
                            10155,
                            8168
                        ]
                    ]
                ],
                "Type": "F"
            },
            {
                "Coordinates": [
                    [
                        [
                            10508,
                            10155,
                            8168
                        ],
                        [
                            10508,
                            10155,
                            0
                        ],
                        [
                            5409,
                            11927,
                            0
                        ],
                        [
                            5409,
                            11927,
                            8168
                        ]
                    ]
                ],
                "Type": "F"
            },
            {
                "Coordinates": [
                    [
                        [
                            814,
                            3138,
                            8168
                        ],
                        [
                            814,
                            3138,
                            0
                        ],
                        [
                            756,
                            3153,
                            0
                        ],
                        [
                            756,
                            3153,
                            8168
                        ]
                    ]
                ],
                "Type": "F"
            },
            {
                "Coordinates": [
                    [
                        [
                            966,
                            3582,
                            8168
                        ],
                        [
                            966,
                            3582,
                            0
                        ],
                        [
                            814,
                            3138,
                            0
                        ],
                        [
                            814,
                            3138,
                            8168
                        ]
                    ]
                ],
                "Type": "F"
            },
            {
                "Coordinates": [
                    [
                        [
                            966,
                            3582,
                            8168
                        ],
                        [
                            814,
                            3138,
                            8168
                        ],
                        [
                            756,
                            3153,
                            8168
                        ],
                        [
                            0,
                            961,
                            8168
                        ],
                        [
                            2800,
                            0,
                            8168
                        ],
                        [
                            3726,
                            2634,
                            8168
                        ],
                        [
                            7411,
                            1370,
                            8168
                        ],
                        [
                            10508,
                            10155,
                            8168
                        ],
                        [
                            5409,
                            11927,
                            8168
                        ],
                        [
                            2304,
                            3123,
                            8168
                        ]
                    ]
                ],
                "Type": "R"
            }
        ]
    }
}