{
  "metadata": {
    "CityObjects": {},
    "metadata": {
      "referenceSystem": "https://www.opengis.net/def/crs/EPSG/0/7415"
    },
    "transform": {
      "scale": [
        0.001,
        0.001,
        0.001
      ],
      "translate": [
        94682.180625,
        433668.877,
        -1.2520001525878897
      ]
    },
    "type": "CityJSON",
    "version": "2.0",
    "vertices": [
      [
        14381,
        7709,
        1253
      ],
      [
        12851,
        8709,
        1253
      ],
      [
        11210,
        6209,
        1253
      ],
      [
        3430,
        11320,
        1253
      ],
      [
        0,
        6110,
        1253
      ],
      [
        9311,
        0,
        1253
      ],
      [
        489,
        6819,
        0
      ],
      [
        2551,
        9735,
        0
      ],
      [
        2437,
        9810,
        0
      ],
      [
        3430,
        11320,
        0
      ],
      [
        11210,
        6209,
        0
      ],
      [
        12851,
        8709,
        0
      ],
      [
        14381,
        7709,
        0
      ],
      [
        12497,
        4846,
        0
      ],
      [
        12339,
        4955,
        0
      ],
      [
        12270,
        4500,
        0
      ],
      [
        9311,
        0,
        0
      ],
      [
        0,
        6110,
        0
      ],
      [
        12851,
        8709,
        8512
      ],
      [
        11210,
        6209,
        8512
      ],
      [
        14381,
        7709,
        8512
      ],
      [
        3430,
        11320,
        8512
      ],
      [
        2551,
        9735,
        8512
      ],
      [
        489,
        6819,
        8512
      ],
      [
        0,
        6110,
        8512
      ],
      [
        9311,
        0,
        8512
      ],
      [
        2437,
        9810,
        8512
      ],
      [
        12270,
        4500,
        8512
      ],
      [
        12339,
        4955,
        8512
      ],
      [
        12497,
        4846,
        8512
      ],
      [
        13179,
        5883,
        0
      ],
      [
        12851,
        8709,
        3505
      ],
      [
        11210,
        6209,
        3505
      ],
      [
        11210,
        6209,
        8517
      ],
      [
        3430,
        11320,
        8517
      ],
      [
        11128,
        6164,
        8517
      ],
      [
        11128,
        6164,
        3505
      ],
      [
        13179,
        5883,
        3505
      ],
      [
        14381,
        7709,
        3505
      ],
      [
        2551,
        9735,
        8517
      ],
      [
        489,
        6819,
        8517
      ],
      [
        9311,
        0,
        8517
      ],
      [
        12270,
        4500,
        8517
      ],
      [
        0,
        6110,
        8517
      ],
      [
        2437,
        9810,
        8517
      ],
      [
        13179,
        5883,
        8517
      ],
      [
        11197,
        6133,
        3505
      ],
      [
        11197,
        6133,
        8517
      ],
      [
        12339,
        4955,
        8517
      ],
      [
        12497,
        4846,
        8517
      ],
      [
        2215,
        9259,
        0
      ],
      [
        11172,
        6235,
        0
      ],
      [
        11413,
        3196,
        0
      ],
      [
        12851,
        8709,
        3492
      ],
      [
        11172,
        6235,
        3452
      ],
      [
        14381,
        7709,
        3535
      ],
      [
        0,
        6110,
        4337
      ],
      [
        9311,
        0,
        4327
      ],
      [
        11413,
        3196,
        9325
      ],
      [
        4737,
        9121,
        8540
      ],
      [
        4737,
        9121,
        7680
      ],
      [
        4794,
        8250,
        8595
      ],
      [
        4841,
        7529,
        9353
      ],
      [
        4841,
        7529,
        8640
      ],
      [
        11172,
        6235,
        6164
      ],
      [
        3430,
        11320,
        6217
      ],
      [
        10967,
        5905,
        6675
      ],
      [
        10967,
        5905,
        8473
      ],
      [
        10200,
        4672,
        8588
      ],
      [
        9901,
        4193,
        8633
      ],
      [
        9901,
        4193,
        9331
      ],
      [
        12270,
        4500,
        7270
      ],
      [
        2215,
        9259,
        9364
      ],
      [
        489,
        6819,
        5462
      ],
      [
        2437,
        9810,
        8597
      ],
      [
        11197,
        6133,
        6259
      ],
      [
        11197,
        6133,
        3453
      ],
      [
        11128,
        6164,
        3451
      ],
      [
        11128,
        6164,
        6274
      ],
      [
        9515,
        6911,
        6629
      ],
      [
        9515,
        6911,
        8471
      ],
      [
        13179,
        5883,
        5090
      ],
      [
        13179,
        5883,
        3507
      ],
      [
        12339,
        4955,
        6720
      ],
      [
        12497,
        4846,
        6725
      ],
      [
        2551,
        9735,
        8597
      ]
    ]
  },
  "buildings": [
    {
      "Pand ID": "0599100000265812",
      "Archetype ID": "TC.1946",
      "Status": "Pand in gebruik",
      "Construction Year": 1920,
      "Number of Floors": 3,
      "Roof Type": "slanted",
      "Wall Area": 242.3,
      "Roof Area (Flat)": 4.88,
      "Roof Area (Sloped)": 109.49,
      "Floor Area": 74.64,
      "Shared Wall Area": 6.42,
      "Ground Elevation (NAP)": -1.253000020980835,
      "LoD 1.2 Data": {
        "Building Height (Mean)": 5.9406561851501465,
        "Building Height (70%)": 7.2071051597595215,
        "Building Height (Max)": 8.483528137207031,
        "Building Height (Min)": 2.212780237197876
      },
      "Boundaries (LoD 1.2)": [
        [
          [
            [
              [
                6,
                7,
                8,
                9,
                10,
                11,
                12,
                13,
                14,
                15,
                16,
                17
              ]
            ],
            [
              [
                18,
                11,
                10,
                19
              ]
            ],
            [
              [
                20,
                12,
                11,
                18
              ]
            ],
            [
              [
                19,
                10,
                9,
                21
              ]
            ],
            [
              [
                22,
                7,
                6,
                23
              ]
            ],
            [
              [
                24,
                17,
                16,
                25
              ]
            ],
            [
              [
                26,
                8,
                7,
                22
              ]
            ],
            [
              [
                21,
                9,
                8,
                26
              ]
            ],
            [
              [
                23,
                6,
                17,
                24
              ]
            ],
            [
              [
                25,
                16,
                15,
                27
              ]
            ],
            [
              [
                28,
                14,
                13,
                29
              ]
            ],
            [
              [
                27,
                15,
                14,
                28
              ]
            ],
            [
              [
                29,
                13,
                12,
                20
              ]
            ],
            [
              [
                29,
                20,
                18,
                19,
                21,
                26,
                22,
                23,
                24,
                25,
                27,
                28
              ]
            ]
          ]
        ]
      ]
    }
  ]
}