{
  "metadata": {
    "CityObjects": {},
    "metadata": {
      "referenceSystem": "https://www.opengis.net/def/crs/EPSG/0/7415"
    },
    "transform": {
      "scale": [
        0.001,
        0.001,
        0.001
      ],
      "translate": [
        89005.3895,
        436599.71875,
        -1.5914989013671885
      ]
    },
    "type": "CityJSON",
    "version": "2.0",
    "vertices": [
      [
        2510,
        10109,
        1592
      ],
      [
        980,
        7099,
        1592
      ],
      [
        1860,
        6649,
        1592
      ],
      [
        0,
        3000,
        1592
      ],
      [
        5911,
        0,
        1592
      ],
      [
        9293,
        6638,
        1592
      ],
      [
        9293,
        6638,
        0
      ],
      [
        5911,
        0,
        0
      ],
      [
        0,
        3000,
        0
      ],
      [
        1860,
        6649,
        0
      ],
      [
        980,
        7099,
        0
      ],
      [
        2510,
        10109,
        0
      ],
      [
        5911,
        0,
        5751
      ],
      [
        9293,
        6638,
        5751
      ],
      [
        980,
        7099,
        5751
      ],
      [
        1860,
        6649,
        5751
      ],
      [
        2510,
        10109,
        5751
      ],
      [
        0,
        3000,
        5751
      ],
      [
        7465,
        7574,
        0
      ],
      [
        7937,
        3978,
        0
      ],
      [
        7465,
        7574,
        5749
      ],
      [
        7465,
        7574,
        3031
      ],
      [
        2510,
        10109,
        5799
      ],
      [
        9293,
        6638,
        2986
      ],
      [
        980,
        7099,
        5791
      ],
      [
        1860,
        6649,
        5782
      ],
      [
        0,
        3000,
        5774
      ],
      [
        5911,
        0,
        5714
      ],
      [
        7937,
        3978,
        2982
      ],
      [
        7937,
        3978,
        5724
      ],
      [
        7161,
        4534,
        3003
      ],
      [
        7161,
        4534,
        5732
      ],
      [
        5481,
        5738,
        5752
      ],
      [
        5481,
        5738,
        3047
      ],
      [
        7081,
        4592,
        5733
      ],
      [
        7081,
        4592,
        3005
      ],
      [
        7111,
        4461,
        3003
      ],
      [
        7111,
        4461,
        5732
      ]
    ]
  },
  "buildings": [
    {
      "Pand ID": "0599100000108543",
      "Archetype ID": "TC.1975-1991",
      "Status": "Pand in gebruik",
      "Construction Year": 1990,
      "Number of Floors": 2,
      "Roof Type": "multiple horizontal",
      "Wall Area": 138.16,
      "Roof Area (Flat)": 52.8,
      "Roof Area (Sloped)": 0.0,
      "Floor Area": 52.79,
      "Shared Wall Area": 37.52,
      "Ground Elevation (NAP)": -1.5920000076293945,
      "LoD 1.2 Data": {
        "Building Height (Mean)": 4.164220809936523,
        "Building Height (70%)": 4.177258491516113,
        "Building Height (Max)": 4.20985221862793,
        "Building Height (Min)": 1.3931447267532349
      },
      "Boundaries (LoD 1.2)": [
        [
          [
            [
              [
                6,
                7,
                8,
                9,
                10,
                11
              ]
            ],
            [
              [
                12,
                7,
                6,
                13
              ]
            ],
            [
              [
                14,
                10,
                9,
                15
              ]
            ],
            [
              [
                16,
                11,
                10,
                14
              ]
            ],
            [
              [
                13,
                6,
                11,
                16
              ]
            ],
            [
              [
                15,
                9,
                8,
                17
              ]
            ],
            [
              [
                17,
                8,
                7,
                12
              ]
            ],
            [
              [
                17,
                12,
                13,
                16,
                14,
                15
              ]
            ]
          ]
        ]
      ]
    }
  ]
}