{
  "metadata": {
    "CityObjects": {},
    "metadata": {
      "referenceSystem": "https://www.opengis.net/def/crs/EPSG/0/7415"
    },
    "transform": {
      "scale": [
        0.001,
        0.001,
        0.001
      ],
      "translate": [
        94004.881,
        433729.86825,
        -1.3149987487792956
      ]
    },
    "type": "CityJSON",
    "version": "2.0",
    "vertices": [
      [
        0,
        14523,
        1315
      ],
      [
        2179,
        0,
        1315
      ],
      [
        4269,
        315,
        1315
      ],
      [
        3280,
        6865,
        1315
      ],
      [
        5549,
        7206,
        1315
      ],
      [
        4369,
        15182,
        1315
      ],
      [
        0,
        14523,
        0
      ],
      [
        4369,
        15182,
        0
      ],
      [
        5549,
        7206,
        0
      ],
      [
        3280,
        6865,
        0
      ],
      [
        4269,
        315,
        0
      ],
      [
        2179,
        0,
        0
      ],
      [
        2179,
        0,
        7205
      ],
      [
        4269,
        315,
        7205
      ],
      [
        3280,
        6865,
        7205
      ],
      [
        5549,
        7206,
        7205
      ],
      [
        4369,
        15182,
        7205
      ],
      [
        0,
        14523,
        7205
      ],
      [
        1244,
        6229,
        0
      ],
      [
        3304,
        6705,
        0
      ],
      [
        2179,
        0,
        3499
      ],
      [
        4269,
        315,
        3499
      ],
      [
        3304,
        6705,
        3499
      ],
      [
        1244,
        6229,
        7829
      ],
      [
        1244,
        6229,
        3499
      ],
      [
        3304,
        6705,
        7829
      ],
      [
        3280,
        6865,
        7829
      ],
      [
        5549,
        7206,
        7829
      ],
      [
        4369,
        15182,
        7829
      ],
      [
        0,
        14523,
        7829
      ],
      [
        638,
        10274,
        0
      ],
      [
        261,
        12783,
        0
      ],
      [
        4649,
        13290,
        0
      ],
      [
        5006,
        10882,
        0
      ],
      [
        2179,
        0,
        3844
      ],
      [
        4269,
        315,
        2723
      ],
      [
        3304,
        6705,
        2719
      ],
      [
        1244,
        6229,
        5092
      ],
      [
        1244,
        6229,
        3836
      ],
      [
        3304,
        6705,
        5249
      ],
      [
        638,
        10274,
        9264
      ],
      [
        3280,
        6865,
        5414
      ],
      [
        5549,
        7206,
        5402
      ],
      [
        261,
        12783,
        6428
      ],
      [
        0,
        14523,
        5649
      ],
      [
        4649,
        13290,
        6470
      ],
      [
        4369,
        15182,
        5622
      ],
      [
        5006,
        10882,
        9191
      ]
    ]
  },
  "buildings": [
    {
      "Pand ID": "0599100000014584",
      "Archetype ID": "TI.1946",
      "Status": "Pand in gebruik",
      "Construction Year": 1921,
      "Number of Floors": 2,
      "Roof Type": "slanted",
      "Wall Area": 69.22,
      "Roof Area (Flat)": 0.0,
      "Roof Area (Sloped)": 64.84,
      "Floor Area": 49.54,
      "Shared Wall Area": 139.29,
      "Ground Elevation (NAP)": -1.315000057220459,
      "LoD 1.2 Data": {
        "Building Height (Mean)": 4.91650390625,
        "Building Height (70%)": 5.979945659637451,
        "Building Height (Max)": 8.175009727478027,
        "Building Height (Min)": 1.2638424634933472
      },
      "Boundaries (LoD 1.2)": [
        [
          [
            [
              [
                6,
                7,
                8,
                9,
                10,
                11
              ]
            ],
            [
              [
                12,
                11,
                10,
                13
              ]
            ],
            [
              [
                13,
                10,
                9,
                14
              ]
            ],
            [
              [
                14,
                9,
                8,
                15
              ]
            ],
            [
              [
                15,
                8,
                7,
                16
              ]
            ],
            [
              [
                17,
                6,
                11,
                12
              ]
            ],
            [
              [
                16,
                7,
                6,
                17
              ]
            ],
            [
              [
                16,
                17,
                12,
                13,
                14,
                15
              ]
            ]
          ]
        ]
      ]
    }
  ]
}